axion_tensorflow/__init__.py
axion_tensorflow/converter.py
axion_tensorflow/fake_quant.py
axion_tensorflow/layers/__init__.py
axion_tensorflow/layers/activation.py
axion_tensorflow/layers/conv2d.py
axion_tensorflow/layers/dense.py
axion_tensorflow/layers/global_average_pooling.py
axion_tensorflow/layers/unpooling.py
axion_tensorflow-0.0.5.dist-info/LICENSE
axion_tensorflow-0.0.5.dist-info/METADATA
axion_tensorflow-0.0.5.dist-info/WHEEL
axion_tensorflow-0.0.5.dist-info/top_level.txt
axion_tensorflow-0.0.5.dist-info/RECORD
