Metadata-Version: 2.1
Name: axion-tensorflow
Version: 0.0.5
Summary: axion for TensorFlow >=2.2.
Home-page: https://github.com/aixin-chip/axion-tensorflow-models
Author: axion
Author-email: axion@aixin-chip.com
License: Apache License 2.0
Platform: UNKNOWN
Classifier: License :: OSI Approved :: Apache Software License
Classifier: Programming Language :: Python :: 3.5
Classifier: Programming Language :: Python :: 3.6
Classifier: Programming Language :: Python :: 3.7
Requires-Python: >=3.5
Requires-Dist: tensorflow (>=2.2)
